ftemplate/FTemplate.py
ftemplate/__init__.py
ftemplate-0.0.1.dist-info/METADATA
ftemplate-0.0.1.dist-info/WHEEL
ftemplate-0.0.1.dist-info/RECORD
